{"atualizado_em": "20/04/2026 14:11", "precos": {"KNCR11": 106.85, "KNIP11": 93.1, "XPML11": 110.76, "HGLG11": 157.86, "BTLG11": 103.92, "KNRI11": 170.94, "MXRF11": 9.92, "XPLG11": 101.99, "VISC11": 110.37, "KNHY11": 100.98, "HGRU11": 131.67, "TRXF11": 91.8, "HGBS11": 20.98, "CPTS11": 8.02, "KNUQ11": 105.44, "GGRC11": 10.17, "RECR11": 83.05, "PVBI11": 77.73, "HSML11": 95.97, "BTHF11": 9.39, "KNHF11": 99.76, "BRCO11": 116.89, "KNSC11": 9.17, "ALZR11": 10.6, "RZTR11": 95.36, "LVBI11": 108.99, "TGAR11": 70.88, "MCCI11": 96.04, "HFOF11": 6.83, "TVRI11": 97.93, "RBVA11": 9.99, "PMLL11": 110.15, "HGCR11": 97.47, "VILG11": 99.67, "HGRE11": 126.57, "VGIR11": 9.8, "PCIP11": 85.89, "RBRR11": 83.8, "JSRE11": 67.33, "RBRX11": 8.76, "BRCR11": 47.99, "GARE11": 8.44, "RBRY11": 93.16, "VRTA11": 79.01, "HSLG11": 91.93, "VGHF11": 6.96, "VCJR11": 80.15, "PSEC11": 62.43, "MCRE11": 9.6, "GTWR11": 85.08, "GZIT11": 44.46, "VGIP11": 80.28, "BTCI11": 9.43, "CPSH11": 10.69, "RZAK11": 85.04, "XPCI11": 84.17, "BROF11": 61.26, "BBIG11": 7.08, "BPML11": 94.12, "KORE11": 73.1, "RBRP11": 52.58, "HABT11": 77.42, "CCME11": 9.12, "TRBL11": 77.8, "RBRL11": 84.26, "JSAF11": 7.87, "KFOF11": 84.3, "ITRI11": 87.62, "BTAL11": 92.67, "AFHI11": 96.48, "RCRB11": 141.01, "MFII11": 69.89, "HCTR11": 20.05, "FATN11": 86.56, "VINO11": 5.1, "URPR11": 33.79, "CLIN11": 93.9, "BCRI11": 64.1, "HTMX11": 137.67, "CACR11": 81.06, "RZAT11": 95.07, "TEPP11": 9.06, "SNCI11": 90.82, "ICRI11": 99.25, "MANA11": 9.35, "BCIA11": 94.35, "LIFE11": 8.68, "VRTM11": 7.37, "DEVA11": 23.51, "RECT11": 39.06, "PATL11": 66.8, "TOPP11": 71.27, "CYCR11": 9.04, "AZPL11": 7.71, "SNEL11": 8.54, "KCRE11": 9.22, "KISU11": 7.08, "PORD11": 8.44, "SNFF11": 74.46, "RPRI11": 85.21, "XPSF11": 6.73, "WHGR11": 9.51, "OUJP11": 87.66, "VGRI11": 6.85, "GRUL11": 8.95, "HSAF11": 80.17, "RBFM11": 10.78, "JSCR11": 8.33, "SPXS11": 8.6, "BLMG11": 32.87, "VIUR11": 2.19, "KIVO11": 64.9, "PMIS11": 8.05, "AJFI11": 8.23, "ARRI11": 6.1, "AIEC11": 61.63, "BTRA11": 67.22, "IBBP11": 7.99}, "variacoes": {"KNCR11": 0.35, "KNIP11": 0.27, "XPML11": -0.31, "HGLG11": 0.2, "BTLG11": -0.15, "KNRI11": -0.09, "MXRF11": 0.51, "XPLG11": 0.3, "VISC11": 0.02, "KNHY11": 0.29, "HGRU11": 0.6, "TRXF11": 0.03, "HGBS11": -0.05, "CPTS11": 0.25, "KNUQ11": 0.34, "GGRC11": -0.1, "RECR11": 0.4, "PVBI11": -0.35, "HSML11": 0.4, "BTHF11": 0.32, "KNHF11": -0.23, "BRCO11": 0.18, "KNSC11": -0.43, "ALZR11": -0.09, "RZTR11": 0.19, "LVBI11": -0.42, "TGAR11": 0.5, "MCCI11": 0.61, "HFOF11": 0.0, "TVRI11": 0.13, "RBVA11": 0.4, "PMLL11": 0.36, "HGCR11": 0.75, "VILG11": 0.47, "HGRE11": -0.02, "VGIR11": 0.41, "PCIP11": 0.98, "RBRR11": 0.78, "JSRE11": 0.4, "RBRX11": 0.23, "BRCR11": 0.1, "GARE11": 0.84, "RBRY11": -0.52, "VRTA11": -0.14, "HSLG11": -0.57, "VGHF11": -0.29, "VCJR11": 0.31, "PSEC11": 0.42, "MCRE11": 0.0, "GTWR11": -0.19, "GZIT11": -0.45, "VGIP11": 0.35, "BTCI11": 0.32, "CPSH11": -0.28, "RZAK11": 0.06, "XPCI11": 0.06, "BROF11": -1.13, "BBIG11": 0.14, "BPML11": -0.14, "KORE11": -0.6, "RBRP11": -0.23, "HABT11": -0.14, "CCME11": -0.76, "TRBL11": -0.22, "RBRL11": 0.57, "JSAF11": 0.13, "KFOF11": 0.37, "ITRI11": 0.78, "BTAL11": -0.09, "AFHI11": 0.62, "RCRB11": -0.06, "MFII11": 0.49, "HCTR11": 0.25, "FATN11": -0.48, "VINO11": -0.78, "URPR11": -1.6, "CLIN11": 0.27, "BCRI11": 0.27, "HTMX11": 0.6, "CACR11": 0.85, "RZAT11": 0.55, "TEPP11": -0.11, "SNCI11": -0.22, "ICRI11": -0.29, "MANA11": -0.32, "BCIA11": -0.68, "LIFE11": -0.23, "VRTM11": 0.0, "DEVA11": 0.17, "RECT11": -0.1, "PATL11": -0.15, "TOPP11": -0.39, "CYCR11": -0.11, "AZPL11": -0.26, "SNEL11": 0.47, "KCRE11": -0.11, "KISU11": -0.14, "PORD11": -0.47, "SNFF11": -0.39, "RPRI11": 0.33, "XPSF11": -0.44, "WHGR11": -0.21, "OUJP11": 0.64, "VGRI11": 3.01, "GRUL11": 0.11, "HSAF11": 0.09, "RBFM11": -0.19, "JSCR11": 0.36, "SPXS11": 0.82, "BLMG11": -0.39, "VIUR11": 2.34, "KIVO11": 0.09, "PMIS11": -0.37, "AJFI11": -0.72, "ARRI11": -0.81, "AIEC11": -0.29, "BTRA11": 0.61, "IBBP11": -0.37}}