{"atualizado_em": "20/04/2026 14:26", "precos": {"KNCR11": 106.87, "KNIP11": 93.14, "XPML11": 110.75, "HGLG11": 157.89, "BTLG11": 103.97, "KNRI11": 170.91, "MXRF11": 9.92, "XPLG11": 101.98, "VISC11": 110.5, "KNHY11": 101.0, "HGRU11": 131.88, "TRXF11": 91.8, "HGBS11": 20.96, "CPTS11": 8.02, "KNUQ11": 105.5, "GGRC11": 10.17, "RECR11": 83.09, "PVBI11": 77.7, "HSML11": 95.98, "BTHF11": 9.38, "KNHF11": 99.78, "BRCO11": 116.9, "KNSC11": 9.17, "ALZR11": 10.6, "RZTR11": 95.07, "LVBI11": 108.96, "TGAR11": 70.9, "MCCI11": 96.15, "HFOF11": 6.83, "TVRI11": 97.95, "RBVA11": 9.99, "PMLL11": 110.15, "HGCR11": 97.48, "VILG11": 99.74, "HGRE11": 126.53, "VGIR11": 9.79, "PCIP11": 86.0, "RBRR11": 83.83, "JSRE11": 67.3, "RBRX11": 8.77, "BRCR11": 47.96, "GARE11": 8.43, "RBRY11": 93.15, "VRTA11": 79.03, "HSLG11": 91.87, "VGHF11": 6.97, "VCJR11": 80.11, "PSEC11": 62.38, "MCRE11": 9.6, "GTWR11": 85.08, "GZIT11": 44.46, "VGIP11": 80.29, "BTCI11": 9.41, "CPSH11": 10.68, "RZAK11": 85.1, "XPCI11": 84.17, "BROF11": 61.26, "BBIG11": 7.07, "BPML11": 94.14, "KORE11": 73.1, "RBRP11": 52.54, "HABT11": 77.42, "CCME11": 9.13, "TRBL11": 77.8, "RBRL11": 84.35, "JSAF11": 7.87, "KFOF11": 84.3, "ITRI11": 87.62, "BTAL11": 92.67, "AFHI11": 96.49, "RCRB11": 140.99, "MFII11": 69.97, "HCTR11": 20.02, "FATN11": 86.57, "VINO11": 5.1, "URPR11": 33.78, "CLIN11": 93.89, "BCRI11": 64.15, "HTMX11": 137.76, "CACR11": 81.04, "RZAT11": 95.16, "TEPP11": 9.06, "SNCI11": 90.82, "ICRI11": 99.25, "MANA11": 9.34, "BCIA11": 94.34, "LIFE11": 8.68, "VRTM11": 7.36, "DEVA11": 23.47, "RECT11": 39.04, "PATL11": 66.8, "TOPP11": 71.49, "CYCR11": 9.04, "AZPL11": 7.7, "SNEL11": 8.53, "KCRE11": 9.22, "KISU11": 7.09, "PORD11": 8.43, "SNFF11": 74.56, "RPRI11": 85.11, "XPSF11": 6.74, "WHGR11": 9.51, "OUJP11": 87.67, "VGRI11": 6.9, "GRUL11": 8.95, "HSAF11": 80.07, "RBFM11": 10.76, "JSCR11": 8.35, "SPXS11": 8.6, "BLMG11": 32.94, "VIUR11": 2.2, "KIVO11": 64.9, "PMIS11": 8.03, "AJFI11": 8.23, "ARRI11": 6.1, "AIEC11": 61.63, "BTRA11": 67.22, "IBBP11": 8.05}, "variacoes": {"KNCR11": 0.37, "KNIP11": 0.31, "XPML11": -0.32, "HGLG11": 0.22, "BTLG11": -0.11, "KNRI11": -0.11, "MXRF11": 0.51, "XPLG11": 0.3, "VISC11": 0.14, "KNHY11": 0.31, "HGRU11": 0.76, "TRXF11": 0.03, "HGBS11": -0.14, "CPTS11": 0.25, "KNUQ11": 0.4, "GGRC11": -0.1, "RECR11": 0.45, "PVBI11": -0.38, "HSML11": 0.41, "BTHF11": 0.21, "KNHF11": -0.21, "BRCO11": 0.19, "KNSC11": -0.43, "ALZR11": -0.09, "RZTR11": -0.12, "LVBI11": -0.45, "TGAR11": 0.52, "MCCI11": 0.72, "HFOF11": 0.0, "TVRI11": 0.15, "RBVA11": 0.4, "PMLL11": 0.36, "HGCR11": 0.76, "VILG11": 0.54, "HGRE11": -0.05, "VGIR11": 0.31, "PCIP11": 1.11, "RBRR11": 0.82, "JSRE11": 0.36, "RBRX11": 0.34, "BRCR11": 0.04, "GARE11": 0.72, "RBRY11": -0.53, "VRTA11": -0.11, "HSLG11": -0.64, "VGHF11": -0.14, "VCJR11": 0.26, "PSEC11": 0.34, "MCRE11": 0.0, "GTWR11": -0.19, "GZIT11": -0.45, "VGIP11": 0.36, "BTCI11": 0.11, "CPSH11": -0.37, "RZAK11": 0.13, "XPCI11": 0.06, "BROF11": -1.13, "BBIG11": 0.0, "BPML11": -0.12, "KORE11": -0.6, "RBRP11": -0.3, "HABT11": -0.14, "CCME11": -0.65, "TRBL11": -0.22, "RBRL11": 0.68, "JSAF11": 0.13, "KFOF11": 0.37, "ITRI11": 0.78, "BTAL11": -0.09, "AFHI11": 0.63, "RCRB11": -0.08, "MFII11": 0.6, "HCTR11": 0.1, "FATN11": -0.47, "VINO11": -0.78, "URPR11": -1.63, "CLIN11": 0.26, "BCRI11": 0.34, "HTMX11": 0.66, "CACR11": 0.82, "RZAT11": 0.65, "TEPP11": -0.11, "SNCI11": -0.22, "ICRI11": -0.29, "MANA11": -0.43, "BCIA11": -0.69, "LIFE11": -0.23, "VRTM11": -0.14, "DEVA11": 0.0, "RECT11": -0.15, "PATL11": -0.15, "TOPP11": -0.08, "CYCR11": -0.11, "AZPL11": -0.39, "SNEL11": 0.35, "KCRE11": -0.11, "KISU11": 0.0, "PORD11": -0.59, "SNFF11": -0.25, "RPRI11": 0.21, "XPSF11": -0.3, "WHGR11": -0.21, "OUJP11": 0.65, "VGRI11": 3.76, "GRUL11": 0.11, "HSAF11": -0.04, "RBFM11": -0.37, "JSCR11": 0.6, "SPXS11": 0.82, "BLMG11": -0.18, "VIUR11": 2.8, "KIVO11": 0.09, "PMIS11": -0.62, "AJFI11": -0.72, "ARRI11": -0.81, "AIEC11": -0.29, "BTRA11": 0.61, "IBBP11": 0.37}}