{"atualizado_em": "24/04/2026 11:36", "precos": {"KNCR11": 106.7, "KNIP11": 93.52, "XPML11": 110.88, "HGLG11": 157.14, "BTLG11": 103.49, "KNRI11": 167.52, "MXRF11": 9.93, "XPLG11": 100.97, "VISC11": 110.17, "KNHY11": 101.17, "HGRU11": 132.79, "TRXF11": 91.76, "HGBS11": 20.98, "CPTS11": 7.94, "KNUQ11": 105.42, "GGRC11": 10.18, "RECR11": 82.96, "PVBI11": 78.92, "HSML11": 95.7, "BTHF11": 9.39, "KNHF11": 99.29, "BRCO11": 117.01, "KNSC11": 9.24, "ALZR11": 10.62, "RZTR11": 95.48, "LVBI11": 109.3, "TGAR11": 70.37, "MCCI11": 96.27, "HFOF11": 6.83, "TVRI11": 98.1, "RBVA11": 9.97, "PMLL11": 110.58, "HGCR11": 97.73, "VILG11": 101.25, "HGRE11": 125.47, "VGIR11": 9.79, "PCIP11": 86.2, "RBRR11": 83.76, "JSRE11": 66.08, "RBRX11": 8.78, "BRCR11": 47.58, "GARE11": 8.39, "RBRY11": 93.13, "VRTA11": 78.63, "HSLG11": 91.8, "VGHF11": 6.91, "VCJR11": 80.29, "PSEC11": 62.0, "MCRE11": 9.71, "GTWR11": 85.25, "GZIT11": 43.5, "VGIP11": 80.54, "BTCI11": 9.39, "CPSH11": 10.63, "RZAK11": 85.47, "XPCI11": 84.18, "BROF11": 62.25, "BBIG11": 7.07, "BPML11": 94.31, "KORE11": 73.52, "RBRP11": 52.26, "HABT11": 77.36, "CCME11": 9.1, "TRBL11": 76.87, "RBRL11": 86.4, "JSAF11": 7.89, "KFOF11": 84.24, "ITRI11": 88.15, "BTAL11": 90.3, "AFHI11": 97.24, "RCRB11": 140.83, "MFII11": 71.1, "HCTR11": 19.47, "FATN11": 86.52, "VINO11": 5.02, "URPR11": 31.63, "CLIN11": 93.01, "BCRI11": 64.42, "HTMX11": 137.73, "CACR11": 81.31, "RZAT11": 96.34, "TEPP11": 9.06, "SNCI11": 90.85, "ICRI11": 99.62, "MANA11": 9.39, "BCIA11": 95.78, "LIFE11": 8.71, "VRTM11": 7.37, "DEVA11": 23.29, "RECT11": 39.06, "PATL11": 66.61, "TOPP11": 71.0, "CYCR11": 9.05, "AZPL11": 7.68, "SNEL11": 8.55, "KCRE11": 9.3, "KISU11": 7.09, "PORD11": 8.45, "SNFF11": 75.46, "RPRI11": 85.75, "XPSF11": 6.77, "WHGR11": 9.55, "OUJP11": 88.27, "VGRI11": 6.68, "GRUL11": 8.96, "HSAF11": 80.62, "RBFM11": 10.83, "JSCR11": 8.41, "SPXS11": 8.62, "BLMG11": 32.74, "VIUR11": 2.21, "KIVO11": 65.05, "PMIS11": 8.08, "AJFI11": 8.26, "ARRI11": 6.09, "AIEC11": 61.55, "BTRA11": 66.4, "IBBP11": 8.03}, "variacoes": {"KNCR11": 0.02, "KNIP11": 0.18, "XPML11": 0.56, "HGLG11": 0.16, "BTLG11": 0.04, "KNRI11": -0.03, "MXRF11": -0.2, "XPLG11": -0.03, "VISC11": 0.15, "KNHY11": -0.18, "HGRU11": 0.07, "TRXF11": 0.03, "HGBS11": 0.19, "CPTS11": -0.13, "KNUQ11": -0.15, "GGRC11": 0.0, "RECR11": 0.01, "PVBI11": 0.99, "HSML11": 0.26, "BTHF11": 0.54, "KNHF11": 0.0, "BRCO11": 0.12, "KNSC11": -0.43, "ALZR11": 0.0, "RZTR11": 0.4, "LVBI11": 0.37, "TGAR11": 0.39, "MCCI11": 0.06, "HFOF11": 0.29, "TVRI11": -0.08, "RBVA11": 0.5, "PMLL11": 0.05, "HGCR11": 0.1, "VILG11": 0.24, "HGRE11": 0.02, "VGIR11": -0.1, "PCIP11": 0.08, "RBRR11": -0.05, "JSRE11": 0.2, "RBRX11": 0.69, "BRCR11": 0.27, "GARE11": -0.12, "RBRY11": 0.69, "VRTA11": -0.47, "HSLG11": -0.13, "VGHF11": -0.14, "VCJR11": -0.67, "PSEC11": -0.02, "MCRE11": 0.31, "GTWR11": 0.11, "GZIT11": -1.29, "VGIP11": 0.09, "BTCI11": 0.21, "CPSH11": 0.09, "RZAK11": 0.27, "XPCI11": -0.01, "BROF11": 0.48, "BBIG11": 0.28, "BPML11": -0.31, "KORE11": 0.49, "RBRP11": -0.55, "HABT11": 0.08, "CCME11": 0.78, "TRBL11": -0.35, "RBRL11": 0.08, "JSAF11": 0.64, "KFOF11": 0.29, "ITRI11": 0.55, "BTAL11": 0.6, "AFHI11": 0.33, "RCRB11": -0.16, "MFII11": -0.36, "HCTR11": -0.51, "FATN11": 0.01, "VINO11": 1.01, "URPR11": -1.68, "CLIN11": -0.01, "BCRI11": -0.12, "HTMX11": 0.24, "CACR11": 0.02, "RZAT11": 0.44, "TEPP11": -0.22, "SNCI11": 0.0, "ICRI11": 0.27, "MANA11": 0.11, "BCIA11": 0.43, "LIFE11": 0.23, "VRTM11": 0.27, "DEVA11": -0.21, "RECT11": 0.03, "PATL11": 0.08, "TOPP11": -0.25, "CYCR11": -0.22, "AZPL11": -0.26, "SNEL11": 0.12, "KCRE11": -0.21, "KISU11": 0.0, "PORD11": 0.12, "SNFF11": 0.15, "RPRI11": -0.26, "XPSF11": 0.3, "WHGR11": 0.1, "OUJP11": -0.32, "VGRI11": -1.04, "GRUL11": 0.56, "HSAF11": 0.32, "RBFM11": -0.28, "JSCR11": -2.66, "SPXS11": 0.23, "BLMG11": -0.15, "VIUR11": 0.0, "KIVO11": 0.15, "PMIS11": -0.37, "AJFI11": -0.84, "ARRI11": -0.33, "AIEC11": -0.02, "BTRA11": -1.88, "IBBP11": 1.52}}