{"atualizado_em": "22/04/2026 13:25", "precos": {"KNCR11": 106.86, "KNIP11": 93.99, "XPML11": 110.35, "HGLG11": 156.98, "BTLG11": 103.61, "KNRI11": 169.01, "MXRF11": 9.92, "XPLG11": 101.5, "VISC11": 110.58, "KNHY11": 101.3, "HGRU11": 133.58, "TRXF11": 91.8, "HGBS11": 20.99, "CPTS11": 8.01, "KNUQ11": 105.86, "GGRC11": 10.24, "RECR11": 82.65, "PVBI11": 78.35, "HSML11": 95.87, "BTHF11": 9.41, "KNHF11": 100.1, "BRCO11": 116.96, "KNSC11": 9.25, "ALZR11": 10.63, "RZTR11": 95.65, "LVBI11": 109.1, "TGAR11": 70.9, "MCCI11": 95.99, "HFOF11": 6.86, "TVRI11": 98.07, "RBVA11": 9.98, "PMLL11": 110.5, "HGCR11": 97.23, "VILG11": 101.41, "HGRE11": 126.79, "VGIR11": 9.79, "PCIP11": 85.9, "RBRR11": 84.2, "JSRE11": 66.7, "RBRX11": 8.77, "BRCR11": 47.3, "GARE11": 8.48, "RBRY11": 92.75, "VRTA11": 79.08, "HSLG11": 91.87, "VGHF11": 6.93, "VCJR11": 81.18, "PSEC11": 62.15, "MCRE11": 9.64, "GTWR11": 85.3, "GZIT11": 44.41, "VGIP11": 80.5, "BTCI11": 9.42, "CPSH11": 10.65, "RZAK11": 85.45, "XPCI11": 84.11, "BROF11": 61.32, "BBIG11": 7.05, "BPML11": 93.99, "KORE11": 73.24, "RBRP11": 52.69, "HABT11": 77.59, "CCME11": 9.22, "TRBL11": 77.95, "RBRL11": 85.91, "JSAF11": 7.87, "KFOF11": 84.42, "ITRI11": 87.16, "BTAL11": 89.54, "AFHI11": 96.41, "RCRB11": 141.24, "MFII11": 70.81, "HCTR11": 19.8, "FATN11": 86.39, "VINO11": 5.1, "URPR11": 33.7, "CLIN11": 92.93, "BCRI11": 64.58, "HTMX11": 137.72, "CACR11": 81.47, "RZAT11": 95.35, "TEPP11": 9.09, "SNCI11": 90.69, "ICRI11": 99.49, "MANA11": 9.36, "BCIA11": 94.3, "LIFE11": 8.69, "VRTM11": 7.36, "DEVA11": 23.45, "RECT11": 39.14, "PATL11": 66.58, "TOPP11": 71.39, "CYCR11": 9.05, "AZPL11": 7.61, "SNEL11": 8.55, "KCRE11": 9.25, "KISU11": 7.09, "PORD11": 8.43, "SNFF11": 74.63, "RPRI11": 85.62, "XPSF11": 6.77, "WHGR11": 9.52, "OUJP11": 88.38, "VGRI11": 6.88, "GRUL11": 9.0, "HSAF11": 80.51, "RBFM11": 10.75, "JSCR11": 8.49, "SPXS11": 8.61, "BLMG11": 32.9, "VIUR11": 2.24, "KIVO11": 65.29, "PMIS11": 8.04, "AJFI11": 8.26, "ARRI11": 6.08, "AIEC11": 61.5, "BTRA11": 67.27, "IBBP11": 8.04}, "variacoes": {"KNCR11": -0.25, "KNIP11": 0.33, "XPML11": -0.41, "HGLG11": -0.58, "BTLG11": -0.38, "KNRI11": -1.0, "MXRF11": -0.3, "XPLG11": -0.21, "VISC11": -0.68, "KNHY11": 0.35, "HGRU11": 0.51, "TRXF11": 0.0, "HGBS11": -0.14, "CPTS11": -0.12, "KNUQ11": 0.34, "GGRC11": -0.19, "RECR11": -0.47, "PVBI11": 0.73, "HSML11": -0.03, "BTHF11": 0.21, "KNHF11": 0.6, "BRCO11": -0.03, "KNSC11": 0.76, "ALZR11": 0.09, "RZTR11": 0.71, "LVBI11": 0.11, "TGAR11": -0.07, "MCCI11": -0.06, "HFOF11": 0.44, "TVRI11": -0.34, "RBVA11": 0.6, "PMLL11": 0.39, "HGCR11": -0.51, "VILG11": 1.61, "HGRE11": 0.09, "VGIR11": -0.2, "PCIP11": 0.01, "RBRR11": 0.38, "JSRE11": -0.71, "RBRX11": 0.11, "BRCR11": -1.4, "GARE11": 0.47, "RBRY11": -0.43, "VRTA11": -0.09, "HSLG11": -0.29, "VGHF11": -0.57, "VCJR11": 0.97, "PSEC11": -0.19, "MCRE11": 0.52, "GTWR11": 0.18, "GZIT11": -0.02, "VGIP11": -0.07, "BTCI11": -0.11, "CPSH11": 0.0, "RZAK11": 0.27, "XPCI11": -0.45, "BROF11": 0.74, "BBIG11": -0.14, "BPML11": -0.93, "KORE11": 0.29, "RBRP11": -0.02, "HABT11": 0.03, "CCME11": 0.88, "TRBL11": -0.42, "RBRL11": 0.35, "JSAF11": 0.51, "KFOF11": -0.45, "ITRI11": 0.16, "BTAL11": -2.67, "AFHI11": -0.18, "RCRB11": -0.25, "MFII11": 1.16, "HCTR11": -0.95, "FATN11": -0.45, "VINO11": 0.0, "URPR11": -0.24, "CLIN11": -0.9, "BCRI11": 0.44, "HTMX11": 0.23, "CACR11": 0.28, "RZAT11": 0.05, "TEPP11": 0.11, "SNCI11": -0.11, "ICRI11": 0.13, "MANA11": -0.11, "BCIA11": -0.05, "LIFE11": -0.23, "VRTM11": -0.27, "DEVA11": -0.17, "RECT11": 0.15, "PATL11": -0.36, "TOPP11": -0.13, "CYCR11": 0.0, "AZPL11": -1.17, "SNEL11": 0.12, "KCRE11": -0.11, "KISU11": 0.0, "PORD11": 0.12, "SNFF11": 0.44, "RPRI11": 0.38, "XPSF11": 0.3, "WHGR11": 0.21, "OUJP11": 0.15, "VGRI11": -0.72, "GRUL11": 0.11, "HSAF11": 0.2, "RBFM11": -0.65, "JSCR11": 1.56, "SPXS11": 0.12, "BLMG11": -0.3, "VIUR11": 2.28, "KIVO11": 0.28, "PMIS11": -0.37, "AJFI11": -0.96, "ARRI11": 0.16, "AIEC11": -0.81, "BTRA11": -0.27, "IBBP11": 1.77}}