{
  "ticker": "PRIF11",
  "dados": {
    "Ticker": "PRIF11",
    "Nome": "Infra Prif",
    "Tipo": "FI-Infra",
    "Setor": "FI-Infra",
    "CNPJ": "58005595000158",
    "Preço Atual": 105.8,
    "Variação Dia": 3.69,
    "P/VP": 1.0012774170470833,
    "VP/cota": 105.6650217,
    "DY a.a.": null,
    "Último Dividendo Pago": null,
    "Retorno - MTD": null,
    "Retorno - 12M": null,
    "Visão Geral": null,
    "Comentário": null,
    "Mês Ref. Comentário": null
  },
  "historico_preco": [],
  "historico_preco_adj": [],
  "historico_dy": [],
  "historico_pvp": [],
  "historico_vp": [
    [
      "2025-01-31",
      101.21835756
    ],
    [
      "2025-02-28",
      101.5269572
    ],
    [
      "2025-03-31",
      102.81168659
    ],
    [
      "2025-04-30",
      103.78815575
    ],
    [
      "2025-05-30",
      104.30148963
    ],
    [
      "2025-06-30",
      105.01702762
    ],
    [
      "2025-07-31",
      103.70292118
    ],
    [
      "2025-08-29",
      104.93730876
    ],
    [
      "2025-09-30",
      106.74204461
    ],
    [
      "2025-10-31",
      107.42530388
    ],
    [
      "2025-11-28",
      108.48029253
    ],
    [
      "2025-12-31",
      107.60508411
    ],
    [
      "2026-01-30",
      107.6513553
    ],
    [
      "2026-02-27",
      107.81988095
    ],
    [
      "2026-03-31",
      106.93005384
    ],
    [
      "2026-04-30",
      105.6650217
    ]
  ],
  "historico_dpc": []
}