{
  "ticker": "CLIN11",
  "ultima_atualizacao": "2026-04-28T14:34:14",
  "fonte": "statusinvest",
  "proventos": [
    {
      "data_com": "2023-11-09",
      "data_pagamento": "2023-11-17",
      "valor": 1.069,
      "tipo": "Rendimento"
    },
    {
      "data_com": "2023-12-08",
      "data_pagamento": "2023-12-15",
      "valor": 1.1,
      "tipo": "Rendimento"
    },
    {
      "data_com": "2024-01-09",
      "data_pagamento": "2024-01-16",
      "valor": 1.01,
      "tipo": "Rendimento"
    },
    {
      "data_com": "2024-02-08",
      "data_pagamento": "2024-02-19",
      "valor": 1.01,
      "tipo": "Rendimento"
    },
    {
      "data_com": "2024-03-08",
      "data_pagamento": "2024-03-15",
      "valor": 1.0,
      "tipo": "Rendimento"
    },
    {
      "data_com": "2024-04-08",
      "data_pagamento": "2024-04-15",
      "valor": 1.02,
      "tipo": "Rendimento"
    },
    {
      "data_com": "2024-05-09",
      "data_pagamento": "2024-05-16",
      "valor": 1.0,
      "tipo": "Rendimento"
    },
    {
      "data_com": "2024-06-10",
      "data_pagamento": "2024-06-17",
      "valor": 0.95,
      "tipo": "Rendimento"
    },
    {
      "data_com": "2024-07-08",
      "data_pagamento": "2024-07-15",
      "valor": 1.0,
      "tipo": "Rendimento"
    },
    {
      "data_com": "2024-08-08",
      "data_pagamento": "2024-08-15",
      "valor": 0.98,
      "tipo": "Rendimento"
    },
    {
      "data_com": "2024-09-09",
      "data_pagamento": "2024-09-16",
      "valor": 0.95,
      "tipo": "Rendimento"
    },
    {
      "data_com": "2024-10-08",
      "data_pagamento": "2024-10-15",
      "valor": 0.95,
      "tipo": "Rendimento"
    },
    {
      "data_com": "2024-11-08",
      "data_pagamento": "2024-11-18",
      "valor": 0.95,
      "tipo": "Rendimento"
    },
    {
      "data_com": "2024-12-09",
      "data_pagamento": "2024-12-16",
      "valor": 1.0,
      "tipo": "Rendimento"
    },
    {
      "data_com": "2025-01-09",
      "data_pagamento": "2025-01-16",
      "valor": 1.0,
      "tipo": "Rendimento"
    },
    {
      "data_com": "2025-02-10",
      "data_pagamento": "2025-02-17",
      "valor": 1.0,
      "tipo": "Rendimento"
    },
    {
      "data_com": "2025-03-12",
      "data_pagamento": "2025-03-19",
      "valor": 1.01,
      "tipo": "Rendimento"
    },
    {
      "data_com": "2025-04-08",
      "data_pagamento": "2025-04-15",
      "valor": 1.1,
      "tipo": "Rendimento"
    },
    {
      "data_com": "2025-05-09",
      "data_pagamento": "2025-05-16",
      "valor": 1.15,
      "tipo": "Rendimento"
    },
    {
      "data_com": "2025-06-09",
      "data_pagamento": "2025-06-16",
      "valor": 1.15,
      "tipo": "Rendimento"
    },
    {
      "data_com": "2025-07-08",
      "data_pagamento": "2025-07-15",
      "valor": 1.1,
      "tipo": "Rendimento"
    },
    {
      "data_com": "2025-08-08",
      "data_pagamento": "2025-08-15",
      "valor": 1.0,
      "tipo": "Rendimento"
    },
    {
      "data_com": "2025-09-08",
      "data_pagamento": "2025-09-15",
      "valor": 1.0,
      "tipo": "Rendimento"
    },
    {
      "data_com": "2025-10-08",
      "data_pagamento": "2025-10-15",
      "valor": 1.0,
      "tipo": "Rendimento"
    },
    {
      "data_com": "2025-11-10",
      "data_pagamento": "2025-11-17",
      "valor": 0.95,
      "tipo": "Rendimento"
    },
    {
      "data_com": "2025-12-08",
      "data_pagamento": "2025-12-15",
      "valor": 0.96,
      "tipo": "Rendimento"
    },
    {
      "data_com": "2026-01-09",
      "data_pagamento": "2026-01-16",
      "valor": 0.95,
      "tipo": "Rendimento"
    },
    {
      "data_com": "2026-02-09",
      "data_pagamento": "2026-02-18",
      "valor": 0.88,
      "tipo": "Rendimento"
    },
    {
      "data_com": "2026-03-09",
      "data_pagamento": "2026-03-16",
      "valor": 0.95,
      "tipo": "Rendimento"
    },
    {
      "data_com": "2026-04-09",
      "data_pagamento": "2026-04-16",
      "valor": 0.95,
      "tipo": "Rendimento"
    }
  ]
}